secret/SCRATCH.py
secret/__init__.py
tests/__init__.py
themebase/__init__.py
themebase/__main__.py
themebase/hooking/__init__.py
themebase/hooking/ante_build_hook.py
themebase/hooking/ante_release_hook.py
themebase/hooking/post_build_hook.py
themebase/hooking/post_release_hook.py
themebase/pyrustic_data/hooking.json
themebase/pyrustic_data/hubstore.json
themebase/pyrustic_data/release_info.json
themebase-0.0.2.dist-info/LICENSE
themebase-0.0.2.dist-info/METADATA
themebase-0.0.2.dist-info/WHEEL
themebase-0.0.2.dist-info/entry_points.txt
themebase-0.0.2.dist-info/top_level.txt
themebase-0.0.2.dist-info/RECORD
