Metadata-Version: 2.1
Name: themebase
Version: 0.0.2
Summary: Create a theme for your Python desktop app
Home-page: https://github.com/pyrustic/themebase
Author: Pyrustic Evangelist
Author-email: pyrustic@protonmail.com
Maintainer: Pyrustic Evangelist
Maintainer-email: pyrustic@protonmail.com
License: MIT
Keywords: library,theme,theming,style,gui,tkinter,desktop-app
Platform: UNKNOWN
Classifier: Programming Language :: Python :: 3
Classifier: License :: OSI Approved :: MIT License
Classifier: Operating System :: OS Independent
Requires-Python: >=3.5
